huaweicloudsdkmastudio/__init__.py
huaweicloudsdkmastudio/v1/__init__.py
huaweicloudsdkmastudio/v1/mastudio_async_client.py
huaweicloudsdkmastudio/v1/mastudio_client.py
huaweicloudsdkmastudio/v1/model/__init__.py
huaweicloudsdkmastudio/v1/model/chat_choice.py
huaweicloudsdkmastudio/v1/model/chat_completion_req.py
huaweicloudsdkmastudio/v1/model/completion_usage.py
huaweicloudsdkmastudio/v1/model/execute_chat_completion_request.py
huaweicloudsdkmastudio/v1/model/execute_chat_completion_response.py
huaweicloudsdkmastudio/v1/model/execute_text_completion_request.py
huaweicloudsdkmastudio/v1/model/execute_text_completion_response.py
huaweicloudsdkmastudio/v1/model/message.py
huaweicloudsdkmastudio/v1/model/message_item.py
huaweicloudsdkmastudio/v1/model/text_choice.py
huaweicloudsdkmastudio/v1/model/text_completion_req.py
huaweicloudsdkmastudio/v1/region/__init__.py
huaweicloudsdkmastudio/v1/region/mastudio_region.py
huaweicloudsdkmastudio-3.1.184.dist-info/METADATA
huaweicloudsdkmastudio-3.1.184.dist-info/WHEEL
huaweicloudsdkmastudio-3.1.184.dist-info/licenses/LICENSE
huaweicloudsdkmastudio-3.1.184.dist-info/RECORD
